{
  "routes": [
    {
      "url": "/authentication/login",
      "method": "GET",
      "queryString": {
        "email": "string",
        "password": "string"
      },
      "response": {
        "idToken": "string",
        "expiresIn": "int32"
      },
      "body": null
    },
    {
      "url": "/company",
      "method": "GET",
      "queryString": null,
      "response": {
        "id": "guid",
        "quickCode": "string",
        "aoc_upload": "string",
        "city": "string",
        "company_address": "string",
        "email": "string",
        "entity": "string",
        "name": "string",
        "personnal_details": "boolean",
        "phone_number": "string",
        "phone_prefix": "string",
        "postcode": "string",
        "represented_by": "string",
        "vat": "string",
        "updated_at": "dateTime",
        "created_at": "dateTime"
      },
      "body": null
    },
    {
      "url": "/company/qc/quickCode:string",
      "method": "GET",
      "queryString": null,
      "response": {
        "id": "guid",
        "quickCode": "string",
        "aoc_upload": "string",
        "city": "string",
        "company_address": "string",
        "email": "string",
        "entity": "string",
        "name": "string",
        "personnal_details": "boolean",
        "phone_number": "string",
        "phone_prefix": "string",
        "postcode": "string",
        "represented_by": "string",
        "vat": "string",
        "updated_at": "dateTime",
        "created_at": "dateTime"
      },
      "body": null
    },
    {
      "url": "/company",
      "method": "POST",
      "queryString": null,
      "response": null,
      "body": {
        "aoc_upload": "string",
        "city": "string",
        "company_address": "string",
        "email": "string",
        "entity": "string",
        "name": "string",
        "personnal_details": "boolean",
        "phone_number": "string",
        "phone_prefix": "string",
        "postcode": "string",
        "represented_by": "string",
        "vat": "string"
      }
    },
    {
      "url": "/company/quickCode:string",
      "method": "PUT",
      "queryString": null,
      "response": null,
      "body": null
    },
    {
      "url": "/company",
      "method": "PUT",
      "queryString": null,
      "response": null,
      "body": {
        "aoc_upload": "string",
        "city": "string",
        "company_address": "string",
        "email": "string",
        "entity": "string",
        "name": "string",
        "personnal_details": "boolean",
        "phone_number": "string",
        "phone_prefix": "string",
        "postcode": "string",
        "represented_by": "string",
        "vat": "string"
      }
    },
    {
      "url": "/flightplan/id:guid",
      "method": "GET",
      "queryString": null,
      "response": {
        "id": "guid",
        "accountId": "guid",
        "companyId": "guid",
        "planeId": "guid",
        "paymentId": "guid",
        "status": "onlineFlightPlanStatus",
        "salesTunnelStep": "string",
        "flightType": "onlineFlightPlanType",
        "favorite": "boolean",
        "legs": [
          {
            "index": "int32",
            "id": "guid",
            "modelId": "guid",
            "callSign": "string",
            "departAirport": {
              "name": "string",
              "iata": "string",
              "oaci": "string",
              "zone1": "boolean",
              "type": "airportType",
              "latitude": "double",
              "longitude": "double",
              "utcOffset": "double",
              "tz": "string",
              "isoCountry": "string",
              "country": "string",
              "city": "string"
            },
            "arrivalAirport": {
              "name": "string",
              "iata": "string",
              "oaci": "string",
              "zone1": "boolean",
              "type": "airportType",
              "latitude": "double",
              "longitude": "double",
              "utcOffset": "double",
              "tz": "string",
              "isoCountry": "string",
              "country": "string",
              "city": "string"
            },
            "departDate": "dateTime",
            "arrivalDate": "dateTime",
            "pax": "int32",
            "crew": "int32"
          }
        ],
        "modelId": "guid",
        "updatedAt": "dateTime",
        "createdAt": "dateTime"
      },
      "body": null
    },
    {
      "url": "/flightplan",
      "method": "GET",
      "queryString": null,
      "response": [
        {
          "id": "guid",
          "accountId": "guid",
          "companyId": "guid",
          "planeId": "guid",
          "paymentId": "guid",
          "status": "onlineFlightPlanStatus",
          "salesTunnelStep": "string",
          "flightType": "onlineFlightPlanType",
          "favorite": "boolean",
          "legs": [
            {
              "index": "int32",
              "id": "guid",
              "modelId": "guid",
              "callSign": "string",
              "departAirport": {
                "name": "string",
                "iata": "string",
                "oaci": "string",
                "zone1": "boolean",
                "type": "airportType",
                "latitude": "double",
                "longitude": "double",
                "utcOffset": "double",
                "tz": "string",
                "isoCountry": "string",
                "country": "string",
                "city": "string"
              },
              "arrivalAirport": {
                "name": "string",
                "iata": "string",
                "oaci": "string",
                "zone1": "boolean",
                "type": "airportType",
                "latitude": "double",
                "longitude": "double",
                "utcOffset": "double",
                "tz": "string",
                "isoCountry": "string",
                "country": "string",
                "city": "string"
              },
              "departDate": "dateTime",
              "arrivalDate": "dateTime",
              "pax": "int32",
              "crew": "int32"
            }
          ],
          "modelId": "guid",
          "updatedAt": "dateTime",
          "createdAt": "dateTime"
        }
      ],
      "body": null
    },
    {
      "url": "/flightplan",
      "method": "POST",
      "queryString": null,
      "response": "guid",
      "body": null
    },
    {
      "url": "/flightplan/flightPlanModelId:guid",
      "method": "PUT",
      "queryString": null,
      "response": "guid",
      "body": null
    },
    {
      "url": "/payment/id:guid",
      "method": "DELETE",
      "queryString": null,
      "response": null,
      "body": null
    },
    {
      "url": "/payment",
      "method": "GET",
      "queryString": null,
      "response": [
        {
          "id": "string",
          "active": "boolean",
          "updatedAt": "dateTime",
          "createdAt": "dateTime",
          "type": "onlinePaymentType",
          "card_holder_name": "string",
          "card_number": "string",
          "card_expiration_date": "string",
          "card_security_code": "string",
          "card_named_on_card": "string",
          "card_type": "string",
          "account_owner": "string",
          "account_name_on": "string",
          "account_iban": "string",
          "account_bic": "string"
        }
      ],
      "body": null
    },
    {
      "url": "/payment",
      "method": "POST",
      "queryString": null,
      "response": null,
      "body": {
        "type": "onlinePaymentType",
        "card_holder_name": "string",
        "card_number": "string",
        "card_expiration_date": "string",
        "card_security_code": "string",
        "card_named_on_card": "string",
        "card_type": "string",
        "account_owner": "string",
        "account_name_on": "string",
        "account_iban": "string",
        "account_bic": "string"
      }
    },
    {
      "url": "/pilot",
      "method": "GET",
      "queryString": null,
      "response": {
        "updatedAt": "dateTime",
        "createdAt": "dateTime",
        "birthdate": "dateTime",
        "birthplace": "string",
        "city": "string",
        "country": "string",
        "firstname": "string",
        "issuing_auth": "string",
        "lastname": "string",
        "passport": "string",
        "passport_expiry": "dateTime",
        "passport_issue": "dateTime",
        "passport_upload": "string",
        "personal_address": "string",
        "phone_number": "string",
        "phone_prefix": "string",
        "postcode": "string"
      },
      "body": null
    },
    {
      "url": "/pilot",
      "method": "POST",
      "queryString": null,
      "response": null,
      "body": {
        "pilot": {
          "birthdate": "dateTime",
          "birthplace": "string",
          "city": "string",
          "country": "string",
          "firstname": "string",
          "issuing_auth": "string",
          "lastname": "string",
          "passport": "string",
          "passport_expiry": "dateTime",
          "passport_issue": "dateTime",
          "passport_upload": "string",
          "personal_address": "string",
          "phone_number": "string",
          "phone_prefix": "string",
          "postcode": "string"
        }
      }
    },
    {
      "url": "/plane",
      "method": "GET",
      "queryString": null,
      "response": [
        {
          "id": "string",
          "updatedAt": "dateTime",
          "createdAt": "dateTime",
          "basic": {
            "registration": "string",
            "engineType": "string",
            "aircraftType": "string",
            "series": "string",
            "serialNumber": "string",
            "units": "boolean",
            "planEasa": "boolean",
            "certifiedEtops": "boolean",
            "rwyLength": "int32",
            "operatingAltitude": "int32",
            "paxSeating": "int32",
            "speedClimbProfile": "string",
            "speedCruiseProfileOne": "string",
            "speedCruiseProfileTwo": "string",
            "speedCruiseProfileThree": "string",
            "speedDescendProfile": "string",
            "speedHoldingProfile": "string"
          },
          "dataEtops": {
            "etopsTime": "int32",
            "etopsEngineNumber": "int32",
            "etopsApuRequire": "boolean",
            "etopsDecompressionAltitude": "int32",
            "etopsOxygen": "int32",
            "etopsMorethanFl450": "boolean"
          },
          "dataFuel": {
            "fuelMax": "int32",
            "fuelTaxi": "int32",
            "fuelApu": "int32",
            "fuelFinalReserveTime": "int32",
            "fuelFinalReserveAmount": "int32",
            "fuelContingencyPct": "int32",
            "fuelContingencyWeight": "int32",
            "fuelMinAlt": "int32",
            "fuelDestApproach": "int32",
            "fuelAltApproach": "int32",
            "fuelCompanyExtra": "int32"
          },
          "dataWeights": {
            "paxMale": "int32",
            "paxFemale": "int32",
            "paxChild": "int32",
            "paxInfant": "int32",
            "paxAdult": "int32",
            "paxLuggage": "int32",
            "mrm": "int32",
            "mtom": "int32",
            "mlm": "int32",
            "mzfm": "int32",
            "domProfileOneName": "string",
            "domProfileOneWeight": "int32",
            "domProfileTwoName": "string",
            "domProfileTwoWeight": "int32",
            "domProfileThreeName": "string",
            "domProfileThreeWeight": "int32"
          },
          "dataAtc": {
            "atcIdent": "string",
            "atcRules": "string",
            "atcFlightType": "string",
            "atcIcao": "string",
            "atcWakeTurbolenceCat": "string",
            "atcEmergencyRadio": "string",
            "atcSurvivalEqpt": "string",
            "atcJackets": "string",
            "atcDinghyNb": "int32",
            "atcDinghyCapacity": "int32",
            "atcDinghyCover": "boolean",
            "atcDinghyColor": "string",
            "atcEquipment": "string",
            "atcTransponder": "string",
            "atcAircraftColor": "string",
            "atcReg": "string",
            "atcSel": "string",
            "atcOpr": "string",
            "atcRmk": "string",
            "atcPbn": "string",
            "atcComments": "string"
          },
          "calcCgLoadsheet": "boolean",
          "dataCalc": {
            "calcWeightingReport": "string",
            "calcFlightEnvelope": "string",
            "calcLoadsheet": "string",
            "calcFueltanks": "string"
          }
        }
      ],
      "body": null
    },
    {
      "url": "/plane/registration",
      "method": "GET",
      "queryString": null,
      "response": [
        {
          "id": "guid",
          "registration": "string"
        }
      ],
      "body": null
    },
    {
      "url": "/plane",
      "method": "POST",
      "queryString": null,
      "response": null,
      "body": {
        "basic": {
          "registration": "string",
          "engineType": "string",
          "aircraftType": "string",
          "series": "string",
          "serialNumber": "string",
          "units": "boolean",
          "planEasa": "boolean",
          "certifiedEtops": "boolean",
          "rwyLength": "int32",
          "operatingAltitude": "int32",
          "paxSeating": "int32",
          "speedClimbProfile": "string",
          "speedCruiseProfileOne": "string",
          "speedCruiseProfileTwo": "string",
          "speedCruiseProfileThree": "string",
          "speedDescendProfile": "string",
          "speedHoldingProfile": "string"
        },
        "dataEtops": {
          "etopsTime": "int32",
          "etopsEngineNumber": "int32",
          "etopsApuRequire": "boolean",
          "etopsDecompressionAltitude": "int32",
          "etopsOxygen": "int32",
          "etopsMorethanFl450": "boolean"
        },
        "dataFuel": {
          "fuelMax": "int32",
          "fuelTaxi": "int32",
          "fuelApu": "int32",
          "fuelFinalReserveTime": "int32",
          "fuelFinalReserveAmount": "int32",
          "fuelContingencyPct": "int32",
          "fuelContingencyWeight": "int32",
          "fuelMinAlt": "int32",
          "fuelDestApproach": "int32",
          "fuelAltApproach": "int32",
          "fuelCompanyExtra": "int32"
        },
        "dataWeights": {
          "paxMale": "int32",
          "paxFemale": "int32",
          "paxChild": "int32",
          "paxInfant": "int32",
          "paxAdult": "int32",
          "paxLuggage": "int32",
          "mrm": "int32",
          "mtom": "int32",
          "mlm": "int32",
          "mzfm": "int32",
          "domProfileOneName": "string",
          "domProfileOneWeight": "int32",
          "domProfileTwoName": "string",
          "domProfileTwoWeight": "int32",
          "domProfileThreeName": "string",
          "domProfileThreeWeight": "int32"
        },
        "dataAtc": {
          "atcIdent": "string",
          "atcRules": "string",
          "atcFlightType": "string",
          "atcIcao": "string",
          "atcWakeTurbolenceCat": "string",
          "atcEmergencyRadio": "string",
          "atcSurvivalEqpt": "string",
          "atcJackets": "string",
          "atcDinghyNb": "int32",
          "atcDinghyCapacity": "int32",
          "atcDinghyCover": "boolean",
          "atcDinghyColor": "string",
          "atcEquipment": "string",
          "atcTransponder": "string",
          "atcAircraftColor": "string",
          "atcReg": "string",
          "atcSel": "string",
          "atcOpr": "string",
          "atcRmk": "string",
          "atcPbn": "string",
          "atcComments": "string"
        },
        "calcCgLoadsheet": "boolean",
        "dataCalc": {
          "calcWeightingReport": "string",
          "calcFlightEnvelope": "string",
          "calcLoadsheet": "string",
          "calcFueltanks": "string"
        }
      }
    },
    {
      "url": "/plane/usingid/id:guid",
      "method": "POST",
      "queryString": null,
      "response": null,
      "body": null
    },
    {
      "url": "/salestunnel/step1/id:guid",
      "method": "GET",
      "queryString": null,
      "response": {
        "currentAircraft": "guid",
        "aircraft": [
          {
            "planeId": "guid",
            "registration": "string"
          }
        ],
        "flightType": "onlineFlightPlanType",
        "legs": [
          {
            "index": "int32",
            "id": "guid?",
            "callSign": "string",
            "departAirport": "string",
            "arrivalAirport": "string",
            "departDate": "dateTime",
            "arrivalDate": "dateTime",
            "pax": "int32",
            "crew": "int32"
          }
        ]
      },
      "body": null
    },
    {
      "url": "/salestunnel/step2/id:guid",
      "method": "GET",
      "queryString": null,
      "response": {
        "genDec": {
          "price": {
            "zero": {
              "zero": {
                "zero": "decimal",
                "one": "decimal",
                "minusOne": "decimal",
                "maxValue": "decimal",
                "minValue": "decimal"
              },
              "one": {
                "zero": "decimal",
                "one": "decimal",
                "minusOne": "decimal",
                "maxValue": "decimal",
                "minValue": "decimal"
              },
              "minusOne": {
                "zero": "decimal",
                "one": "decimal",
                "minusOne": "decimal",
                "maxValue": "decimal",
                "minValue": "decimal"
              },
              "maxValue": {
                "zero": "decimal",
                "one": "decimal",
                "minusOne": "decimal",
                "maxValue": "decimal",
                "minValue": "decimal"
              },
              "minValue": {
                "zero": "decimal",
                "one": "decimal",
                "minusOne": "decimal",
                "maxValue": "decimal",
                "minValue": "decimal"
              }
            },
            "one": {
              "zero": {
                "zero": "decimal",
                "one": "decimal",
                "minusOne": "decimal",
                "maxValue": "decimal",
                "minValue": "decimal"
              },
              "one": {
                "zero": "decimal",
                "one": "decimal",
                "minusOne": "decimal",
                "maxValue": "decimal",
                "minValue": "decimal"
              },
              "minusOne": {
                "zero": "decimal",
                "one": "decimal",
                "minusOne": "decimal",
                "maxValue": "decimal",
                "minValue": "decimal"
              },
              "maxValue": {
                "zero": "decimal",
                "one": "decimal",
                "minusOne": "decimal",
                "maxValue": "decimal",
                "minValue": "decimal"
              },
              "minValue": {
                "zero": "decimal",
                "one": "decimal",
                "minusOne": "decimal",
                "maxValue": "decimal",
                "minValue": "decimal"
              }
            },
            "minusOne": {
              "zero": {
                "zero": "decimal",
                "one": "decimal",
                "minusOne": "decimal",
                "maxValue": "decimal",
                "minValue": "decimal"
              },
              "one": {
                "zero": "decimal",
                "one": "decimal",
                "minusOne": "decimal",
                "maxValue": "decimal",
                "minValue": "decimal"
              },
              "minusOne": {
                "zero": "decimal",
                "one": "decimal",
                "minusOne": "decimal",
                "maxValue": "decimal",
                "minValue": "decimal"
              },
              "maxValue": {
                "zero": "decimal",
                "one": "decimal",
                "minusOne": "decimal",
                "maxValue": "decimal",
                "minValue": "decimal"
              },
              "minValue": {
                "zero": "decimal",
                "one": "decimal",
                "minusOne": "decimal",
                "maxValue": "decimal",
                "minValue": "decimal"
              }
            },
            "maxValue": {
              "zero": {
                "zero": "decimal",
                "one": "decimal",
                "minusOne": "decimal",
                "maxValue": "decimal",
                "minValue": "decimal"
              },
              "one": {
                "zero": "decimal",
                "one": "decimal",
                "minusOne": "decimal",
                "maxValue": "decimal",
                "minValue": "decimal"
              },
              "minusOne": {
                "zero": "decimal",
                "one": "decimal",
                "minusOne": "decimal",
                "maxValue": "decimal",
                "minValue": "decimal"
              },
              "maxValue": {
                "zero": "decimal",
                "one": "decimal",
                "minusOne": "decimal",
                "maxValue": "decimal",
                "minValue": "decimal"
              },
              "minValue": {
                "zero": "decimal",
                "one": "decimal",
                "minusOne": "decimal",
                "maxValue": "decimal",
                "minValue": "decimal"
              }
            },
            "minValue": {
              "zero": {
                "zero": "decimal",
                "one": "decimal",
                "minusOne": "decimal",
                "maxValue": "decimal",
                "minValue": "decimal"
              },
              "one": {
                "zero": "decimal",
                "one": "decimal",
                "minusOne": "decimal",
                "maxValue": "decimal",
                "minValue": "decimal"
              },
              "minusOne": {
                "zero": "decimal",
                "one": "decimal",
                "minusOne": "decimal",
                "maxValue": "decimal",
                "minValue": "decimal"
              },
              "maxValue": {
                "zero": "decimal",
                "one": "decimal",
                "minusOne": "decimal",
                "maxValue": "decimal",
                "minValue": "decimal"
              },
              "minValue": {
                "zero": "decimal",
                "one": "decimal",
                "minusOne": "decimal",
                "maxValue": "decimal",
                "minValue": "decimal"
              }
            }
          },
          "description": "string",
          "quantity": "int32"
        },
        "fuel": {
          "price": {
            "zero": {
              "zero": {
                "zero": "decimal",
                "one": "decimal",
                "minusOne": "decimal",
                "maxValue": "decimal",
                "minValue": "decimal"
              },
              "one": {
                "zero": "decimal",
                "one": "decimal",
                "minusOne": "decimal",
                "maxValue": "decimal",
                "minValue": "decimal"
              },
              "minusOne": {
                "zero": "decimal",
                "one": "decimal",
                "minusOne": "decimal",
                "maxValue": "decimal",
                "minValue": "decimal"
              },
              "maxValue": {
                "zero": "decimal",
                "one": "decimal",
                "minusOne": "decimal",
                "maxValue": "decimal",
                "minValue": "decimal"
              },
              "minValue": {
                "zero": "decimal",
                "one": "decimal",
                "minusOne": "decimal",
                "maxValue": "decimal",
                "minValue": "decimal"
              }
            },
            "one": {
              "zero": {
                "zero": "decimal",
                "one": "decimal",
                "minusOne": "decimal",
                "maxValue": "decimal",
                "minValue": "decimal"
              },
              "one": {
                "zero": "decimal",
                "one": "decimal",
                "minusOne": "decimal",
                "maxValue": "decimal",
                "minValue": "decimal"
              },
              "minusOne": {
                "zero": "decimal",
                "one": "decimal",
                "minusOne": "decimal",
                "maxValue": "decimal",
                "minValue": "decimal"
              },
              "maxValue": {
                "zero": "decimal",
                "one": "decimal",
                "minusOne": "decimal",
                "maxValue": "decimal",
                "minValue": "decimal"
              },
              "minValue": {
                "zero": "decimal",
                "one": "decimal",
                "minusOne": "decimal",
                "maxValue": "decimal",
                "minValue": "decimal"
              }
            },
            "minusOne": {
              "zero": {
                "zero": "decimal",
                "one": "decimal",
                "minusOne": "decimal",
                "maxValue": "decimal",
                "minValue": "decimal"
              },
              "one": {
                "zero": "decimal",
                "one": "decimal",
                "minusOne": "decimal",
                "maxValue": "decimal",
                "minValue": "decimal"
              },
              "minusOne": {
                "zero": "decimal",
                "one": "decimal",
                "minusOne": "decimal",
                "maxValue": "decimal",
                "minValue": "decimal"
              },
              "maxValue": {
                "zero": "decimal",
                "one": "decimal",
                "minusOne": "decimal",
                "maxValue": "decimal",
                "minValue": "decimal"
              },
              "minValue": {
                "zero": "decimal",
                "one": "decimal",
                "minusOne": "decimal",
                "maxValue": "decimal",
                "minValue": "decimal"
              }
            },
            "maxValue": {
              "zero": {
                "zero": "decimal",
                "one": "decimal",
                "minusOne": "decimal",
                "maxValue": "decimal",
                "minValue": "decimal"
              },
              "one": {
                "zero": "decimal",
                "one": "decimal",
                "minusOne": "decimal",
                "maxValue": "decimal",
                "minValue": "decimal"
              },
              "minusOne": {
                "zero": "decimal",
                "one": "decimal",
                "minusOne": "decimal",
                "maxValue": "decimal",
                "minValue": "decimal"
              },
              "maxValue": {
                "zero": "decimal",
                "one": "decimal",
                "minusOne": "decimal",
                "maxValue": "decimal",
                "minValue": "decimal"
              },
              "minValue": {
                "zero": "decimal",
                "one": "decimal",
                "minusOne": "decimal",
                "maxValue": "decimal",
                "minValue": "decimal"
              }
            },
            "minValue": {
              "zero": {
                "zero": "decimal",
                "one": "decimal",
                "minusOne": "decimal",
                "maxValue": "decimal",
                "minValue": "decimal"
              },
              "one": {
                "zero": "decimal",
                "one": "decimal",
                "minusOne": "decimal",
                "maxValue": "decimal",
                "minValue": "decimal"
              },
              "minusOne": {
                "zero": "decimal",
                "one": "decimal",
                "minusOne": "decimal",
                "maxValue": "decimal",
                "minValue": "decimal"
              },
              "maxValue": {
                "zero": "decimal",
                "one": "decimal",
                "minusOne": "decimal",
                "maxValue": "decimal",
                "minValue": "decimal"
              },
              "minValue": {
                "zero": "decimal",
                "one": "decimal",
                "minusOne": "decimal",
                "maxValue": "decimal",
                "minValue": "decimal"
              }
            }
          },
          "description": "string",
          "quantity": "int32"
        },
        "flightPackage": [
          {
            "order": "int32",
            "departAirport": "string",
            "arrivalAirport": "string",
            "priceId": "guid",
            "price": {
              "zero": {
                "zero": {
                  "zero": "decimal",
                  "one": "decimal",
                  "minusOne": "decimal",
                  "maxValue": "decimal",
                  "minValue": "decimal"
                },
                "one": {
                  "zero": "decimal",
                  "one": "decimal",
                  "minusOne": "decimal",
                  "maxValue": "decimal",
                  "minValue": "decimal"
                },
                "minusOne": {
                  "zero": "decimal",
                  "one": "decimal",
                  "minusOne": "decimal",
                  "maxValue": "decimal",
                  "minValue": "decimal"
                },
                "maxValue": {
                  "zero": "decimal",
                  "one": "decimal",
                  "minusOne": "decimal",
                  "maxValue": "decimal",
                  "minValue": "decimal"
                },
                "minValue": {
                  "zero": "decimal",
                  "one": "decimal",
                  "minusOne": "decimal",
                  "maxValue": "decimal",
                  "minValue": "decimal"
                }
              },
              "one": {
                "zero": {
                  "zero": "decimal",
                  "one": "decimal",
                  "minusOne": "decimal",
                  "maxValue": "decimal",
                  "minValue": "decimal"
                },
                "one": {
                  "zero": "decimal",
                  "one": "decimal",
                  "minusOne": "decimal",
                  "maxValue": "decimal",
                  "minValue": "decimal"
                },
                "minusOne": {
                  "zero": "decimal",
                  "one": "decimal",
                  "minusOne": "decimal",
                  "maxValue": "decimal",
                  "minValue": "decimal"
                },
                "maxValue": {
                  "zero": "decimal",
                  "one": "decimal",
                  "minusOne": "decimal",
                  "maxValue": "decimal",
                  "minValue": "decimal"
                },
                "minValue": {
                  "zero": "decimal",
                  "one": "decimal",
                  "minusOne": "decimal",
                  "maxValue": "decimal",
                  "minValue": "decimal"
                }
              },
              "minusOne": {
                "zero": {
                  "zero": "decimal",
                  "one": "decimal",
                  "minusOne": "decimal",
                  "maxValue": "decimal",
                  "minValue": "decimal"
                },
                "one": {
                  "zero": "decimal",
                  "one": "decimal",
                  "minusOne": "decimal",
                  "maxValue": "decimal",
                  "minValue": "decimal"
                },
                "minusOne": {
                  "zero": "decimal",
                  "one": "decimal",
                  "minusOne": "decimal",
                  "maxValue": "decimal",
                  "minValue": "decimal"
                },
                "maxValue": {
                  "zero": "decimal",
                  "one": "decimal",
                  "minusOne": "decimal",
                  "maxValue": "decimal",
                  "minValue": "decimal"
                },
                "minValue": {
                  "zero": "decimal",
                  "one": "decimal",
                  "minusOne": "decimal",
                  "maxValue": "decimal",
                  "minValue": "decimal"
                }
              },
              "maxValue": {
                "zero": {
                  "zero": "decimal",
                  "one": "decimal",
                  "minusOne": "decimal",
                  "maxValue": "decimal",
                  "minValue": "decimal"
                },
                "one": {
                  "zero": "decimal",
                  "one": "decimal",
                  "minusOne": "decimal",
                  "maxValue": "decimal",
                  "minValue": "decimal"
                },
                "minusOne": {
                  "zero": "decimal",
                  "one": "decimal",
                  "minusOne": "decimal",
                  "maxValue": "decimal",
                  "minValue": "decimal"
                },
                "maxValue": {
                  "zero": "decimal",
                  "one": "decimal",
                  "minusOne": "decimal",
                  "maxValue": "decimal",
                  "minValue": "decimal"
                },
                "minValue": {
                  "zero": "decimal",
                  "one": "decimal",
                  "minusOne": "decimal",
                  "maxValue": "decimal",
                  "minValue": "decimal"
                }
              },
              "minValue": {
                "zero": {
                  "zero": "decimal",
                  "one": "decimal",
                  "minusOne": "decimal",
                  "maxValue": "decimal",
                  "minValue": "decimal"
                },
                "one": {
                  "zero": "decimal",
                  "one": "decimal",
                  "minusOne": "decimal",
                  "maxValue": "decimal",
                  "minValue": "decimal"
                },
                "minusOne": {
                  "zero": "decimal",
                  "one": "decimal",
                  "minusOne": "decimal",
                  "maxValue": "decimal",
                  "minValue": "decimal"
                },
                "maxValue": {
                  "zero": "decimal",
                  "one": "decimal",
                  "minusOne": "decimal",
                  "maxValue": "decimal",
                  "minValue": "decimal"
                },
                "minValue": {
                  "zero": "decimal",
                  "one": "decimal",
                  "minusOne": "decimal",
                  "maxValue": "decimal",
                  "minValue": "decimal"
                }
              }
            },
            "zone1": "boolean"
          }
        ]
      },
      "body": null
    },
    {
      "url": "/salestunnel/step3/id:guid",
      "method": "GET",
      "queryString": null,
      "response": {
        "legs": [
          {
            "id": "guid",
            "departAirport": "string",
            "arrivalAirport": "string",
            "handling": [
              {}
            ]
          }
        ]
      },
      "body": null
    },
    {
      "url": "/salestunnel/step4/id:guid",
      "method": "GET",
      "queryString": null,
      "response": {
        "legs": [
          {
            "id": "guid",
            "departAirport": "string",
            "arrivalAirport": "string",
            "meals": [
              {
                "id": "guid",
                "service": "string",
                "comment": "string",
                "pax": "int32",
                "crew": "int32"
              }
            ]
          }
        ]
      },
      "body": null
    },
    {
      "url": "/salestunnel/step5/id:guid",
      "method": "GET",
      "queryString": null,
      "response": {
        "legs": [
          {
            "id": "guid",
            "departAirport": "string",
            "arrivalAirport": {
              "name": "string",
              "iata": "string",
              "oaci": "string",
              "zone1": "boolean",
              "type": "airportType",
              "latitude": "double",
              "longitude": "double",
              "utcOffset": "double",
              "tz": "string",
              "isoCountry": "string",
              "country": "string",
              "city": "string"
            },
            "reservations": [
              {
                "id": "guid",
                "price": "string",
                "providerId": "guid",
                "travel": {
                  "pickup": "dateTime",
                  "origin": {
                    "name": "string",
                    "iata": "string",
                    "oaci": "string",
                    "zone1": "boolean",
                    "type": "airportType",
                    "latitude": "double",
                    "longitude": "double",
                    "utcOffset": "double",
                    "tz": "string",
                    "isoCountry": "string",
                    "country": "string",
                    "city": "string"
                  },
                  "destination": "string",
                  "destinationLocation": {
                    "longitude": "double",
                    "latitude": "double"
                  }
                },
                "car": {
                  "title": "string",
                  "category": "string",
                  "samples": "string",
                  "imageWeb": "string",
                  "imageLogo": "string",
                  "imageMobilelogo": "string",
                  "passengers": "int32",
                  "bagages": "int32"
                },
                "pax": "boolean"
              }
            ]
          }
        ]
      },
      "body": null
    },
    {
      "url": "/salestunnel/step5search",
      "method": "GET",
      "queryString": {
        "pickup": "dateTime",
        "airport": "string",
        "destination": "string",
        "destinationLocation": "geoCodeLocation"
      },
      "response": {
        "results": [
          {
            "providerId": "guid"
          }
        ]
      },
      "body": null
    },
    {
      "url": "/salestunnel/step6/id:guid",
      "method": "GET",
      "queryString": null,
      "response": {
        "legs": [
          {
            "id": "guid",
            "departAirport": "string",
            "arrivalAirport": "string",
            "booking": [
              {
                "hotelRate": "int32",
                "pax": "boolean",
                "checkIn": "dateTime",
                "checkOut": "dateTime",
                "where": "aera",
                "placeId": "string",
                "booking": "int32[]"
              }
            ]
          }
        ]
      },
      "body": null
    },
    {
      "url": "/salestunnel/step7/id:guid",
      "method": "GET",
      "queryString": null,
      "response": {
        "comments": "string"
      },
      "body": null
    },
    {
      "url": "/salestunnel/step1",
      "method": "POST",
      "queryString": null,
      "response": null,
      "body": {
        "id": "guid",
        "planeId": "guid",
        "flightType": "onlineFlightPlanType",
        "legs": [
          {
            "index": "int32",
            "id": "guid?",
            "callSign": "string",
            "departAirport": "string",
            "arrivalAirport": "string",
            "departDate": "dateTime",
            "arrivalDate": "dateTime",
            "pax": "int32",
            "crew": "int32"
          }
        ]
      }
    },
    {
      "url": "/salestunnel/step2",
      "method": "POST",
      "queryString": null,
      "response": null,
      "body": {
        "id": "guid",
        "genDec": {
          "quantity": "int32"
        },
        "fuel": {
          "quantity": "int32"
        }
      }
    },
    {
      "url": "/salestunnel/step3",
      "method": "POST",
      "queryString": null,
      "response": null,
      "body": {
        "id": "guid",
        "legs": [
          {
            "id": "guid",
            "handling": [
              {
                "service": "string",
                "quantity": "int32"
              }
            ]
          }
        ]
      }
    },
    {
      "url": "/salestunnel/step4",
      "method": "POST",
      "queryString": null,
      "response": null,
      "body": {
        "id": "guid",
        "legs": [
          {
            "id": "guid",
            "meals": [
              {
                "id": "guid",
                "service": "string",
                "comment": "string",
                "pax": "int32",
                "crew": "int32"
              }
            ]
          }
        ]
      }
    },
    {
      "url": "/salestunnel/step5",
      "method": "POST",
      "queryString": null,
      "response": null,
      "body": {
        "id": "guid",
        "legs": [
          {
            "id": "guid",
            "reservations": [
              {
                "id": "guid",
                "providerId": "guid"
              }
            ]
          }
        ]
      }
    },
    {
      "url": "/salestunnel/step6",
      "method": "POST",
      "queryString": null,
      "response": null,
      "body": {
        "id": "guid",
        "legs": [
          {
            "id": "guid",
            "booking": [
              {
                "hotelRate": "int32",
                "pax": "boolean",
                "checkIn": "dateTime",
                "checkOut": "dateTime",
                "where": "aera",
                "placeId": "string",
                "booking": "int32[]"
              }
            ]
          }
        ]
      }
    },
    {
      "url": "/salestunnel/step7",
      "method": "POST",
      "queryString": null,
      "response": null,
      "body": {
        "id": "guid",
        "comments": "string"
      }
    },
    {
      "url": "/users",
      "method": "GET",
      "queryString": null,
      "response": {
        "isPilotSet": "boolean",
        "isCompanySet": "boolean",
        "isPlaneSet": "boolean",
        "isPaymentSet": "boolean",
        "status": "string",
        "userId": "guid",
        "lastLogin": "dateTime",
        "lastPasswordReset": "dateTime",
        "tokenExpiration": "dateTime",
        "tokenIssuedAt": "dateTime",
        "updatedAt": "dateTime",
        "createdAt": "dateTime",
        "registrationAcknowledged": "boolean"
      },
      "body": null
    },
    {
      "url": "/users/create",
      "method": "POST",
      "queryString": null,
      "response": null,
      "body": {
        "email": "string",
        "resultUrl": "string"
      }
    },
    {
      "url": "/users/acknowledged",
      "method": "PUT",
      "queryString": null,
      "response": null,
      "body": null
    }
  ],
  "enums": {
    "onlineFlightPlanStatus": {
      "draft": 0,
      "error": 1,
      "ok": 2
    },
    "onlineFlightPlanType": {
      "ferry": 0,
      "business": 1,
      "commercial": 2
    },
    "airportType": {
      "closed": 0,
      "balloonport": 1,
      "heliport": 2,
      "smallAirport": 3,
      "mediumAirport": 4,
      "largeAirport": 5,
      "seaplaneBase": 6
    },
    "onlinePaymentType": {
      "card": 0,
      "account": 1
    },
    "aera": {
      "airport": 0,
      "downtown": 1,
      "other": 2
    }
  },
  "types": {
    "decimal": {
      "zero": "decimal",
      "one": "decimal",
      "minusOne": "decimal",
      "maxValue": "decimal",
      "minValue": "decimal"
    },
    "geoCodeLocation": {
      "longitude": "double",
      "latitude": "double"
    }
  }
}